spk/__init__.py
spk/spk.py
spk-0.0.1.dist-info/METADATA
spk-0.0.1.dist-info/WHEEL
spk-0.0.1.dist-info/top_level.txt
spk-0.0.1.dist-info/RECORD
