Metadata-Version: 2.1
Name: spk
Version: 0.0.1
Summary: Simple package for making the program speak
Home-page: UNKNOWN
Author: Aditya Singh
Author-email: <mail@yusiferzendric.com>
License: UNKNOWN
Keywords: python,speaking,simple speaking,speak,bot speaking
Platform: UNKNOWN
Classifier: Development Status :: 1 - Planning
Classifier: Intended Audience :: Developers
Classifier: Programming Language :: Python :: 3
Classifier: Operating System :: Unix
Classifier: Operating System :: MacOS :: MacOS X
Classifier: Operating System :: Microsoft :: Windows
Requires-Dist: pyttsx3
